{
    "shootoutc/ackermann": {
        "Firefox": {
            "browser": "Mozilla/5.0 (Android 12; Mobile; rv:121.0) Gecko/121.0 Firefox/121.0",
            "device": "Linux aarch64",
            "url": "shootoutc/ackermann",
            "access": "2024-02-25T07:46:17.599Z",
            "status": "success",
            "times": [
                {
                    "label": "page loaded",
                    "time": "2.000",
                    "delta": "2.000"
                },
                {
                    "label": "wasm initialized",
                    "time": "63.000",
                    "delta": "61.000"
                },
                {
                    "label": "wasm benchmark",
                    "time": "609.000",
                    "delta": "546.000"
                },
                {
                    "label": "wasm benchmark",
                    "time": "1133.000",
                    "delta": "524.000"
                },
                {
                    "label": "wasm benchmark",
                    "time": "1654.000",
                    "delta": "521.000"
                }
            ]
        }
    },
    "stanford/realmm": {
        "Firefox": {
            "browser": "Mozilla/5.0 (Android 12; Mobile; rv:121.0) Gecko/121.0 Firefox/121.0",
            "device": "Linux aarch64",
            "url": "stanford/realmm",
            "access": "2024-02-25T07:42:49.487Z",
            "status": "success",
            "times": [
                {
                    "label": "page loaded",
                    "time": "5.000",
                    "delta": "5.000"
                },
                {
                    "label": "wasm initialized",
                    "time": "52.000",
                    "delta": "47.000"
                },
                {
                    "label": "wasm benchmark",
                    "time": "53.000",
                    "delta": "1.000"
                },
                {
                    "label": "wasm benchmark",
                    "time": "54.000",
                    "delta": "1.000"
                },
                {
                    "label": "wasm benchmark",
                    "time": "55.000",
                    "delta": "1.000"
                }
            ]
        }
    },
    "shootoutc/matrix": {
        "Firefox": {
            "browser": "Mozilla/5.0 (Android 12; Mobile; rv:121.0) Gecko/121.0 Firefox/121.0",
            "device": "Linux aarch64",
            "url": "shootoutc/matrix",
            "access": "2024-02-25T07:48:46.642Z",
            "status": "success",
            "times": [
                {
                    "label": "page loaded",
                    "time": "3.000",
                    "delta": "3.000"
                },
                {
                    "label": "wasm initialized",
                    "time": "263.000",
                    "delta": "260.000"
                },
                {
                    "label": "wasm benchmark",
                    "time": "7217.000",
                    "delta": "6954.000"
                },
                {
                    "label": "wasm benchmark",
                    "time": "11695.000",
                    "delta": "4478.000"
                },
                {
                    "label": "wasm benchmark",
                    "time": "14856.000",
                    "delta": "3161.000"
                }
            ]
        }
    },
    "shootoutc/nestedloop": {
        "Firefox": {
            "browser": "Mozilla/5.0 (Android 12; Mobile; rv:121.0) Gecko/121.0 Firefox/121.0",
            "device": "Linux aarch64",
            "url": "shootoutc/nestedloop",
            "access": "2024-02-25T07:52:48.445Z",
            "status": "success",
            "times": [
                {
                    "label": "page loaded",
                    "time": "2.000",
                    "delta": "2.000"
                },
                {
                    "label": "wasm initialized",
                    "time": "93.000",
                    "delta": "91.000"
                },
                {
                    "label": "wasm benchmark",
                    "time": "93.000",
                    "delta": "0.000"
                },
                {
                    "label": "wasm benchmark",
                    "time": "94.000",
                    "delta": "1.000"
                },
                {
                    "label": "wasm benchmark",
                    "time": "94.000",
                    "delta": "0.000"
                }
            ]
        }
    }
}